hedgehog_station_controller-0.2.dist-info/DESCRIPTION.rst
hedgehog_station_controller-0.2.dist-info/METADATA
hedgehog_station_controller-0.2.dist-info/RECORD
hedgehog_station_controller-0.2.dist-info/WHEEL
hedgehog_station_controller-0.2.dist-info/metadata.json
hedgehog_station_controller-0.2.dist-info/top_level.txt
visaweb/__init__.py
visaweb/admin.py
visaweb/apps.py
visaweb/models.py
visaweb/tests.py
visaweb/urls.py
visaweb/views.py
visaweb/migrations/0001_initial.py
visaweb/migrations/0002_auto_20170311_1614.py
visaweb/migrations/0003_auto_20170311_1626.py
visaweb/migrations/0004_auto_20170311_1657.py
visaweb/migrations/0005_auto_20170311_1658.py
visaweb/migrations/0006_auto_20170311_1658.py
visaweb/migrations/0007_auto_20170311_1723.py
visaweb/migrations/0008_auto_20170311_1724.py
visaweb/migrations/0009_auto_20170311_2115.py
visaweb/migrations/0010_auto_20170311_2115.py
visaweb/migrations/0011_auto_20170311_2116.py
visaweb/migrations/0012_auto_20170311_2124.py
visaweb/migrations/0013_auto_20170311_2125.py
visaweb/migrations/0014_auto_20170311_2127.py
visaweb/migrations/__init__.py
visaweb/static/visaweb/style.css
visaweb/templates/visaweb/base_generic.html
visaweb/templates/visaweb/detail.html
visaweb/templates/visaweb/index.html
visaweb/templates/visaweb/results.html
webconsole/__init__.py
webconsole/settings.py
webconsole/urls.py
webconsole/wsgi.py
